repo2img/__init__.py
repo2img/main.py
repo2img/cli/decode.py
repo2img/cli/encode.py
repo2img/core/archiver.py
repo2img/core/crypto.py
repo2img/core/decoder.py
repo2img/core/encoder.py
repo2img/utils/hash.py
repo2img/utils/io_helpers.py
repo2img-1.0.3.dist-info/METADATA
repo2img-1.0.3.dist-info/WHEEL
repo2img-1.0.3.dist-info/entry_points.txt
repo2img-1.0.3.dist-info/top_level.txt
repo2img-1.0.3.dist-info/RECORD
