Metadata-Version: 2.4
Name: repo2img
Version: 1.0.3
Summary: A high-performance CLI tool to convert a code repository into a single, compressed, and encrypted image and back.
Author-email: Your Name <you@example.com>
Classifier: Programming Language :: Python :: 3
Classifier: License :: OSI Approved :: MIT License
Classifier: Operating System :: OS Independent
Classifier: Topic :: Software Development :: Build Tools
Classifier: Topic :: System :: Archiving :: Compression
Classifier: Topic :: Utilities
Requires-Python: >=3.8
Requires-Dist: Pillow
Requires-Dist: numpy
Requires-Dist: cryptography
Requires-Dist: zstandard
